README.rst
setup.py
bin/roboclone
roboclone/__init__.py
roboclone/eclipse.py
roboclone/git.py
roboclone/main.py
roboclone/templates.py
roboclone.egg-info/PKG-INFO
roboclone.egg-info/SOURCES.txt
roboclone.egg-info/dependency_links.txt
roboclone.egg-info/requires.txt
roboclone.egg-info/top_level.txt